pylibcrypt/__init__.py
pylibcrypt-1.0.0.dist-info/METADATA
pylibcrypt-1.0.0.dist-info/WHEEL
pylibcrypt-1.0.0.dist-info/top_level.txt
pylibcrypt-1.0.0.dist-info/RECORD
