Metadata-Version: 2.1
Name: pylibcrypt
Version: 1.0.0
Summary: Hello World
Home-page: UNKNOWN
Author: NHJonas
Author-email: nick.faltermeier@gmx.de
License: UNKNOWN
Keywords: python
Platform: UNKNOWN
Classifier: Operating System :: Microsoft :: Windows
